LICENSE
MANIFEST.in
README.md
setup.py
pydjamodb/__init__.py
pydjamodb/attributes.py
pydjamodb/connection.py
pydjamodb/models.py
pydjamodb/queryset.py
pydjamodb/test_runner.py
pydjamodb.egg-info/PKG-INFO
pydjamodb.egg-info/SOURCES.txt
pydjamodb.egg-info/dependency_links.txt
pydjamodb.egg-info/not-zip-safe
pydjamodb.egg-info/requires.txt
pydjamodb.egg-info/top_level.txt